perfscope/__init__.py
perfscope/config.py
perfscope/profiler.py
perfscope/py.typed
perfscope-1.0.6.dist-info/licenses/LICENSE
perfscope-1.0.6.dist-info/METADATA
perfscope-1.0.6.dist-info/WHEEL
perfscope-1.0.6.dist-info/top_level.txt
perfscope-1.0.6.dist-info/RECORD
