Metadata-Version: 2.4
Name: perfscope
Version: 1.0.6
Summary: The Ultimate Python Performance Profiler & APM Tool - Production-Ready Performance Monitoring, Memory Tracking, Call Tree Analysis & Bottleneck Detection for Django, Flask, FastAPI, Async Applications, Data Science & Machine Learning
Author: Sattyam Jain
Maintainer: Sattyam Jain
License: MIT License
Project-URL: Homepage, https://github.com/sattyamjain/perfscope
Project-URL: Documentation, https://github.com/sattyamjain/perfscope#readme
Project-URL: Repository, https://github.com/sattyamjain/perfscope.git
Project-URL: Source Code, https://github.com/sattyamjain/perfscope
Project-URL: Bug Tracker, https://github.com/sattyamjain/perfscope/issues
Project-URL: Issue Tracker, https://github.com/sattyamjain/perfscope/issues
Project-URL: Feature Requests, https://github.com/sattyamjain/perfscope/issues/new?template=feature_request.md
Project-URL: Bug Reports, https://github.com/sattyamjain/perfscope/issues/new?template=bug_report.md
Project-URL: Changelog, https://github.com/sattyamjain/perfscope/releases
Project-URL: Download, https://pypi.org/project/perfscope/
Project-URL: PyPI, https://pypi.org/project/perfscope/
Project-URL: Funding, https://github.com/sponsors/sattyamjain
Project-URL: Discussions, https://github.com/sattyamjain/perfscope/discussions
Keywords: profiling,profiler,performance,monitoring,apm,application-performance-monitoring,debugging,tracing,instrumentation,analytics,metrics,benchmarking,memory,memory-profiling,memory-leak,memory-usage,memory-tracking,gc,garbage-collection,resource-monitoring,cpu-profiling,cpu-usage,resource-usage,async,asyncio,await,concurrent,threading,multiprocessing,coroutine,django,flask,fastapi,starlette,tornado,bottle,pyramid,web-framework,wsgi,asgi,web-application,api,rest-api,microservices,data-scien
Classifier: Development Status :: 5 - Production/Stable
Classifier: Intended Audience :: Developers
Classifier: Intended Audience :: System Administrators
Classifier: Intended Audience :: Information Technology
Classifier: Intended Audience :: Science/Research
Classifier: Operating System :: OS Independent
Classifier: Operating System :: POSIX :: Linux
Classifier: Operating System :: Microsoft :: Windows
Classifier: Operating System :: MacOS
Classifier: Programming Language :: Python
Classifier: Programming Language :: Python :: 3
Classifier: Programming Language :: Python :: 3.8
Classifier: Programming Language :: Python :: 3.9
Classifier: Programming Language :: Python :: 3.10
Classifier: Programming Language :: Python :: 3.11
Classifier: Programming Language :: Python :: 3.12
Classifier: Programming Language :: Python :: 3 :: Only
Classifier: Programming Language :: Python :: Implementation :: CPython
Classifier: Programming Language :: Python :: Implementation :: PyPy
Classifier: Topic :: Software Development :: Libraries :: Python Modules
Classifier: Topic :: Software Development :: Debuggers
Classifier: Topic :: Software Development :: Quality Assurance
Classifier: Topic :: Software Development :: Testing
Classifier: Topic :: System :: Monitoring
Classifier: Topic :: System :: Systems Administration
Classifier: Topic :: System :: Benchmark
Classifier: Topic :: System :: Logging
Classifier: Topic :: Internet :: WWW/HTTP :: Dynamic Content
Classifier: Topic :: Internet :: WWW/HTTP :: HTTP Servers
Classifier: Topic :: Scientific/Engineering
Classifier: Topic :: Scientific/Engineering :: Information Analysis
Classifier: Framework :: AsyncIO
Classifier: Framework :: Django
Classifier: Framework :: Flask
Classifier: Environment :: Web Environment
Classifier: Environment :: Console
Classifier: Natural Language :: English
Classifier: Typing :: Typed
Requires-Python: >=3.8
License-File: LICENSE
Provides-Extra: full
Requires-Dist: psutil>=5.9.0; extra == "full"
Provides-Extra: dev
Requires-Dist: pytest>=7.4.0; extra == "dev"
Requires-Dist: pytest-cov>=4.1.0; extra == "dev"
Requires-Dist: pytest-asyncio>=0.21.0; extra == "dev"
Requires-Dist: pytest-benchmark>=4.0.0; extra == "dev"
Requires-Dist: pytest-xdist>=3.3.0; extra == "dev"
Requires-Dist: psutil>=5.9.0; extra == "dev"
Requires-Dist: ruff>=0.1.0; extra == "dev"
Requires-Dist: mypy>=1.5.0; extra == "dev"
Requires-Dist: types-psutil>=5.9.0; extra == "dev"
Requires-Dist: mkdocs>=1.5.0; extra == "dev"
Requires-Dist: mkdocs-material>=9.0.0; extra == "dev"
Requires-Dist: build>=0.10.0; extra == "dev"
Requires-Dist: twine>=4.0.0; extra == "dev"
Requires-Dist: pre-commit>=3.0.0; extra == "dev"
Requires-Dist: tox>=4.0.0; extra == "dev"
Provides-Extra: web
Requires-Dist: django>=3.2; extra == "web"
Requires-Dist: flask>=2.0.0; extra == "web"
Requires-Dist: fastapi>=0.100.0; extra == "web"
Requires-Dist: starlette>=0.27.0; extra == "web"
Requires-Dist: aiohttp>=3.8.0; extra == "web"
Provides-Extra: science
Requires-Dist: numpy>=1.21.0; extra == "science"
Requires-Dist: pandas>=1.5.0; extra == "science"
Requires-Dist: matplotlib>=3.5.0; extra == "science"
Requires-Dist: jupyter>=1.0.0; extra == "science"
Provides-Extra: all
Requires-Dist: psutil>=5.9.0; extra == "all"
Requires-Dist: django>=3.2; extra == "all"
Requires-Dist: flask>=2.0.0; extra == "all"
Requires-Dist: fastapi>=0.100.0; extra == "all"
Requires-Dist: numpy>=1.21.0; extra == "all"
Requires-Dist: pandas>=1.5.0; extra == "all"
Requires-Dist: matplotlib>=3.5.0; extra == "all"
Dynamic: license-file
